setup.py
sxbwc_toolbox/__init__.py
sxbwc_toolbox.egg-info/PKG-INFO
sxbwc_toolbox.egg-info/SOURCES.txt
sxbwc_toolbox.egg-info/dependency_links.txt
sxbwc_toolbox.egg-info/top_level.txt
sxbwc_toolbox/base/base_admin.py
sxbwc_toolbox/base/base_export_admin.py
sxbwc_toolbox/base/base_export_resource.py
sxbwc_toolbox/base/base_import_admin.py
sxbwc_toolbox/base/base_model.py
sxbwc_toolbox/tools/datetime_util.py
sxbwc_toolbox/tools/export_util.py
sxbwc_toolbox/tools/jsonresponse_util.py
sxbwc_toolbox/tools/mail_util.py
sxbwc_toolbox/tools/md5_util.py
sxbwc_toolbox/tools/message_util.py
sxbwc_toolbox/tools/permission_util.py
sxbwc_toolbox/tools/pinyin_util.py
sxbwc_toolbox/tools/pycharts_util.py
sxbwc_toolbox/tools/random_util.py
sxbwc_toolbox/tools/sms_util.py
sxbwc_toolbox/tools/weixin_template_util.py